nvidia/nvimgcodec/extensions/libnvpnm_ext.so.0.6.0
nvidia/nvimgcodec/__init__.py
nvidia/nvimgcodec/include/nvcv_adapter.hpp
nvidia/nvimgcodec/extensions/libnvbmp_ext.so.0.6.0
nvidia_nvimgcodec_tegra_cu13-0.6.0.32.dist-info/LICENSE.txt
nvidia/nvimgcodec/include/nvimgcodec.h
nvidia/nvimgcodec/include/nvimgcodec_version.h
nvidia_nvimgcodec_tegra_cu13-0.6.0.32.dist-info/METADATA
nvidia_nvimgcodec_tegra_cu13-0.6.0.32.dist-info/top_level.txt
nvidia/__init__.py
nvidia/nvimgcodec/extensions/libtiff_ext.so.0.6.0
nvidia/nvimgcodec/extensions/libjpeg_turbo_ext.so.0.6.0
nvidia_nvimgcodec_tegra_cu13-0.6.0.32.dist-info/WHEEL
nvidia/nvimgcodec/extensions/libopencv_ext.so.0.6.0
nvidia/nvimgcodec/extensions/libnvjpeg2k_ext.so.0.6.0
nvidia/nvimgcodec/extensions/libnvjpeg_ext.so.0.6.0
nvidia/nvimgcodec/extensions/libnvtiff_ext.so.0.6.0
nvidia/nvimgcodec/libnvimgcodec.so.0
nvidia/nvimgcodec/nvimgcodec_impl.cpython-39-aarch64-linux-gnu.so
nvidia/nvimgcodec/nvimgcodec_impl.cpython-310-aarch64-linux-gnu.so
nvidia/nvimgcodec/nvimgcodec_impl.cpython-312-aarch64-linux-gnu.so
nvidia/nvimgcodec/nvimgcodec_impl.cpython-313-aarch64-linux-gnu.so
nvidia/nvimgcodec/nvimgcodec_impl.cpython-311-aarch64-linux-gnu.so
nvidia_nvimgcodec_tegra_cu13-0.6.0.32.dist-info/RECORD
