Metadata-Version: 2.1
Name: nvidia-nvimgcodec-tegra-cu13
Version: 0.6.0.32
Summary: NVIDIA nvimgcodec tegra for CUDA 13. Git SHA: 
Home-page: https://github.com/NVIDIA/nvImageCodec
Author: NVIDIA Corporation
License: Apache License 2.0
Platform: UNKNOWN
Classifier: Programming Language :: Python :: 3.8
Classifier: Programming Language :: Python :: 3.9
Classifier: Programming Language :: Python :: 3.10
Classifier: Programming Language :: Python :: 3.11
Classifier: Programming Language :: Python :: 3.12
Classifier: Programming Language :: Python :: 3.13
Requires-Python: >=3.8, <3.14
Provides-Extra: all
Requires-Dist: nvidia-nvjpeg2k-tegra-cu12 ; extra == 'all'
Requires-Dist: nvidia-nvtiff-tegra-cu12 ; extra == 'all'
Provides-Extra: nvjpeg2k
Requires-Dist: nvidia-nvjpeg2k-tegra-cu12 ; extra == 'nvjpeg2k'
Provides-Extra: nvtiff
Requires-Dist: nvidia-nvtiff-tegra-cu12 ; extra == 'nvtiff'
